{"frames":[{"pos":[18,29],"size":[13,12],"origin":[-7,3]},{"pos":[22,1],"size":[18,12],"origin":[-9,3]},{"pos":[1,44],"size":[12,11],"origin":[-6,3]},{"pos":[33,29],"size":[12,13],"origin":[-6,3]},{"pos":[47,42],"size":[12,12],"origin":[-6,3]},{"pos":[16,43],"size":[13,11],"origin":[-6,3]},{"pos":[1,1],"size":[19,13],"origin":[-9,3]},{"pos":[80,1],"size":[16,12],"origin":[-7,3]},{"pos":[42,1],"size":[17,12],"origin":[-7,3]},{"pos":[1,16],"size":[15,12],"origin":[-6,3]},{"pos":[77,15],"size":[14,13],"origin":[-6,2]},{"pos":[1,30],"size":[13,12],"origin":[-6,3]},{"pos":[18,29],"size":[13,12],"origin":[-7,3]},{"pos":[74,41],"size":[14,11],"origin":[-7,2]},{"pos":[90,41],"size":[14,11],"origin":[-6,-1]},{"pos":[90,41],"size":[14,11],"origin":[-6,-1]},{"pos":[98,1],"size":[1,1],"origin":[-50,89]},{"pos":[98,1],"size":[1,1],"origin":[-50,89]},{"pos":[98,1],"size":[1,1],"origin":[-50,89]},{"pos":[98,1],"size":[1,1],"origin":[-50,89]},{"pos":[98,1],"size":[1,1],"origin":[-50,89]},{"pos":[98,1],"size":[1,1],"origin":[-50,89]},{"pos":[98,1],"size":[1,1],"origin":[-50,89]},{"pos":[74,30],"size":[17,9],"origin":[-5,10]},{"pos":[22,15],"size":[16,12],"origin":[-7,3]},{"pos":[40,15],"size":[16,12],"origin":[-7,4]},{"pos":[58,15],"size":[17,11],"origin":[-6,3]},{"pos":[61,1],"size":[17,12],"origin":[-7,3]},{"pos":[58,28],"size":[14,12],"origin":[-7,3]}],"image":"player/pants/greenBunnyPants.png"}

